devdeck_slack/__init__.py
devdeck_slack/slack_away_control.py
devdeck_slack/slack_deck.py
devdeck_slack/slack_dnd_control.py
devdeck_slack/slack_online_control.py
devdeck_slack/slack_status_control.py
devdeck_slack/assets/away.png
devdeck_slack/assets/online.png
devdeck_slack/assets/slack.png
tests/__init__.py
tests/testing_utils.py
tests/devdeck_slack/__init__.py
tests/devdeck_slack/test_slack_away_control.py
tests/devdeck_slack/test_slack_dnd_control.py
tests/devdeck_slack/test_slack_online_control.py
tests/devdeck_slack/test_slack_status_control.py
devdeck_slack-1.0.5.dist-info/METADATA
devdeck_slack-1.0.5.dist-info/WHEEL
devdeck_slack-1.0.5.dist-info/top_level.txt
devdeck_slack-1.0.5.dist-info/RECORD
