Metadata-Version: 2.1
Name: devdeck-slack
Version: 1.0.5
Summary: Slack deck and controls for DevDeck.
Home-page: https://github.com/jamesridgway/devdeck-slack
Author: James Ridgway
License: MIT
Platform: UNKNOWN
Requires-Dist: assertpy
Requires-Dist: devdeck-core (==1.0.7)
Requires-Dist: pytest
Requires-Dist: slack-sdk (==3.1.0)
Requires-Dist: parsedatetime
Requires-Dist: tzlocal
